Metadata-Version: 2.1
Name: django-rest-permission
Version: 0.1.4
Summary: Access control for APIView of djangorestframework base on properties of request's method and view's action.
Home-page: https://github.com/PyDa5/django-rest-permission
Author: PyDa5
Author-email: 1174446068@qq.com
License: MIT License
Platform: UNKNOWN
Classifier: Development Status :: 4 - Beta
Classifier: Programming Language :: Python :: 3
Requires: django
Requires: djangorestframework
